aiothrottler.py
aiothrottler-0.0.16.dist-info/LICENSE
aiothrottler-0.0.16.dist-info/METADATA
aiothrottler-0.0.16.dist-info/WHEEL
aiothrottler-0.0.16.dist-info/top_level.txt
aiothrottler-0.0.16.dist-info/RECORD
